.DS_Store
pybundletool/__init__.py
pybundletool/bundletool.py
pybundletool/configs.py
pybundletool/errors.py
pybundletool/utils.py
pybundletool/binary-files/aapt2
pybundletool/binary-files/bundletool
pybundletool-0.0.1.dev2.dist-info/LICENSE
pybundletool-0.0.1.dev2.dist-info/METADATA
pybundletool-0.0.1.dev2.dist-info/WHEEL
pybundletool-0.0.1.dev2.dist-info/top_level.txt
pybundletool-0.0.1.dev2.dist-info/RECORD
