Metadata-Version: 2.1
Name: pybundletool
Version: 0.0.1.dev2
Summary: Android bundletool functionalities in python.
Home-page: https://github.com/appknox/pybundletool
Author: Appknox
Author-email: engineering@appknox.com
Project-URL: Bug Tracker, https://github.com/appknox/pybundletool/issues
Classifier: Development Status :: 1 - Planning
Classifier: Intended Audience :: Developers
Classifier: Topic :: Software Development :: Libraries
Classifier: License :: OSI Approved :: MIT License
Classifier: Programming Language :: Python :: 3.7
Classifier: Programming Language :: Python :: 3.8
Classifier: Programming Language :: Python :: 3.9
Classifier: Programming Language :: Python :: 3.10
Requires-Python: >=3.7
License-File: LICENSE
